reader/__init__.py
reader/feed.py
second/__init__.py
second/watzpoppin.py
lmbr_reader-1.0.1.dist-info/LICENSE
lmbr_reader-1.0.1.dist-info/METADATA
lmbr_reader-1.0.1.dist-info/WHEEL
lmbr_reader-1.0.1.dist-info/entry_points.txt
lmbr_reader-1.0.1.dist-info/top_level.txt
lmbr_reader-1.0.1.dist-info/RECORD
