Metadata-Version: 2.1
Name: lmbr-reader
Version: 1.0.1
Summary: Read the z - lmbr
Home-page: https://github.com/realpython/second
Author: Lmbr
Author-email: lmbr@lmbr.com
License: MIT
Platform: UNKNOWN
Classifier: License :: OSI Approved :: MIT License
Classifier: Programming Language :: Python
Classifier: Programming Language :: Python :: 2
Classifier: Programming Language :: Python :: 3
